nebulizer/__init__.py
nebulizer/cli.py
nebulizer/core.py
nebulizer/deprecated_cli.py
nebulizer/groups.py
nebulizer/libraries.py
nebulizer/options.py
nebulizer/quotas.py
nebulizer/search.py
nebulizer/tools.py
nebulizer/toolshed.py
nebulizer/users.py
nebulizer-0.7.1.dist-info/LICENSE
nebulizer-0.7.1.dist-info/METADATA
nebulizer-0.7.1.dist-info/WHEEL
nebulizer-0.7.1.dist-info/entry_points.txt
nebulizer-0.7.1.dist-info/top_level.txt
nebulizer-0.7.1.dist-info/RECORD
