Metadata-Version: 2.1
Name: nebulizer
Version: 0.7.1
Summary: CLI for remote admin of Galaxy servers
Home-page: https://github.com/pjbriggs/nebulizer
Maintainer: Peter Briggs
Maintainer-email: peter.briggs@manchester.ac.uk
License: AFL
Platform: Posix; MacOS X; Windows
Classifier: Development Status :: 4 - Beta
Classifier: Environment :: Console
Classifier: Intended Audience :: End Users/Desktop
Classifier: Intended Audience :: System Administrators
Classifier: Intended Audience :: Developers
Classifier: License :: OSI Approved :: Academic Free License (AFL)
Classifier: Operating System :: OS Independent
Classifier: Topic :: Scientific/Engineering
Classifier: Topic :: Scientific/Engineering :: Bio-Informatics
Classifier: Programming Language :: Python :: 3
Classifier: Programming Language :: Python :: 3.6
Classifier: Programming Language :: Python :: 3.7
Classifier: Programming Language :: Python :: 3.8
Classifier: Programming Language :: Python :: 3.9
Classifier: Programming Language :: Python :: 3 :: Only
Requires-Python: >=3.6
License-File: LICENSE
Requires-Dist: bioblend (==0.15.0)
Requires-Dist: mako
Requires-Dist: click (==7.1.2)
